sst_url_shortener/__init__.py
sst_url_shortener/_base_client.py
sst_url_shortener/_client.py
sst_url_shortener/_compat.py
sst_url_shortener/_constants.py
sst_url_shortener/_exceptions.py
sst_url_shortener/_files.py
sst_url_shortener/_models.py
sst_url_shortener/_qs.py
sst_url_shortener/_resource.py
sst_url_shortener/_response.py
sst_url_shortener/_streaming.py
sst_url_shortener/_types.py
sst_url_shortener/_version.py
sst_url_shortener/py.typed
sst_url_shortener/_utils/__init__.py
sst_url_shortener/_utils/_logs.py
sst_url_shortener/_utils/_proxy.py
sst_url_shortener/_utils/_reflection.py
sst_url_shortener/_utils/_streams.py
sst_url_shortener/_utils/_sync.py
sst_url_shortener/_utils/_transform.py
sst_url_shortener/_utils/_typing.py
sst_url_shortener/_utils/_utils.py
sst_url_shortener/lib/.keep
sst_url_shortener/resources/__init__.py
sst_url_shortener/resources/urls.py
sst_url_shortener/types/__init__.py
sst_url_shortener/types/short_url.py
sst_url_shortener/types/short_url_count_result.py
sst_url_shortener/types/short_url_search_result.py
sst_url_shortener/types/url_create_params.py
sst_url_shortener/types/url_create_response.py
sst_url_shortener/types/url_delete_by_original_url_params.py
sst_url_shortener/types/url_delete_by_short_id_params.py
sst_url_shortener/types/url_from_original_url_params.py
sst_url_shortener/types/url_from_original_url_response.py
sst_url_shortener/types/url_from_short_id_params.py
sst_url_shortener/types/url_from_short_id_response.py
sst_url_shortener/types/url_quick_count_response.py
sst_url_shortener/types/url_search_params.py
sst_url_shortener/types/url_search_response.py
sst_url_shortener/types/url_slow_count_response.py
sst_url_shortener-1.0.0.dist-info/METADATA
sst_url_shortener-1.0.0.dist-info/WHEEL
sst_url_shortener-1.0.0.dist-info/licenses/LICENSE
sst_url_shortener-1.0.0.dist-info/RECORD
